tfrecord_lite.cp36-win_amd64.pyd
tfrecord_lite-0.0.6.dist-info/LICENSE
tfrecord_lite-0.0.6.dist-info/METADATA
tfrecord_lite-0.0.6.dist-info/WHEEL
tfrecord_lite-0.0.6.dist-info/top_level.txt
tfrecord_lite-0.0.6.dist-info/RECORD
