Metadata-Version: 1.2
Name: tfrecord-lite
Version: 0.0.6
Summary: A lightweight tfrecord parser
Home-page: https://github.com/jongwook/tfrecord_lite
Author: Jong Wook Kim
Author-email: jongwook@nyu.edu
License: MIT
Project-URL: Source, https://github.com/jongwook/tfrecord_lite
Project-URL: Tracker, https://github.com/jongwook/tfrecord_lite/issues
Keywords: tfrecord
Platform: UNKNOWN
Classifier: Development Status :: 3 - Alpha
Classifier: Intended Audience :: Developers
Classifier: License :: OSI Approved :: MIT License
Classifier: Programming Language :: Python :: 3
Classifier: Programming Language :: Python :: 3.6
Requires-Python: >=3.6
